setup.py
demo_diffusion/__init__.py
demo_diffusion/dd_argparse.py
demo_diffusion/dynamic_import.py
demo_diffusion/engine.py
demo_diffusion/utils_modelopt.py
demo_diffusion.egg-info/PKG-INFO
demo_diffusion.egg-info/SOURCES.txt
demo_diffusion.egg-info/dependency_links.txt
demo_diffusion.egg-info/not-zip-safe
demo_diffusion.egg-info/top_level.txt
demo_diffusion/image/__init__.py
demo_diffusion/image/load.py
demo_diffusion/image/resize.py
demo_diffusion/image/video.py
demo_diffusion/model/__init__.py
demo_diffusion/model/base_model.py
demo_diffusion/model/clip.py
demo_diffusion/model/diffusion_transformer.py
demo_diffusion/model/gan.py
demo_diffusion/model/load.py
demo_diffusion/model/lora.py
demo_diffusion/model/optimizer.py
demo_diffusion/model/scheduler.py
demo_diffusion/model/t5.py
demo_diffusion/model/tokenizer.py
demo_diffusion/model/unet.py
demo_diffusion/model/vae.py
demo_diffusion/path/__init__.py
demo_diffusion/path/dd_path.py
demo_diffusion/path/resolve_path.py
demo_diffusion/pipeline/__init__.py
demo_diffusion/pipeline/calibrate.py
demo_diffusion/pipeline/diffusion_pipeline.py
demo_diffusion/pipeline/flux_pipeline.py
demo_diffusion/pipeline/model_memory_manager.py
demo_diffusion/pipeline/stable_cascade_pipeline.py
demo_diffusion/pipeline/stable_diffusion_35_pipeline.py
demo_diffusion/pipeline/stable_diffusion_3_pipeline.py
demo_diffusion/pipeline/stable_diffusion_pipeline.py
demo_diffusion/pipeline/stable_video_diffusion_pipeline.py
demo_diffusion/pipeline/type.py
demo_diffusion/utils_sd3/__init__.py
demo_diffusion/utils_sd3/mmdit.py
demo_diffusion/utils_sd3/other_impls.py
demo_diffusion/utils_sd3/sd3_impls.py